Workbook

Sheet Summary
A1: Dinner for Two - Seattle Catalog (live coverage)
A2: Verified June 19, 2026. 'Live' = Enriched & web-verified open. Counts auto-update from the Restaurants sheet.
A4: Status | B4: Count
A5: Live (Enriched) | B5: =COUNTIF(Restaurants!$AK$3:$AK$98,"Enriched") -> 71
A6: Closed - drop | B6: =COUNTIF(Restaurants!$AK$3:$AK$98,"CLOSED - drop") -> 17
A7: Needs review | B7: =COUNTIF(Restaurants!$AK$3:$AK$98,"Review") -> 8
A8: TOTAL | B8: =COUNTA(Restaurants!$C$3:$C$98) -> 96
A10: Live by Neighborhood | D10: Live by Price Tier
A11: Neighborhood | B11: Live | D11: Tier | E11: Live
A12: Capitol Hill | B12: =COUNTIFS(Restaurants!$C$3:$C$98,"Capitol Hill",Restaurants!$AK$3:$AK$98,"Enriched") -> 8 | D12: $ | E12: =COUNTIFS(Restaurants!$F$3:$F$98,"$",Restaurants!$AK$3:$AK$98,"Enriched") -> 7
A13: Ballard | B13: =COUNTIFS(Restaurants!$C$3:$C$98,"Ballard",Restaurants!$AK$3:$AK$98,"Enriched") -> 6 | D13: $$ | E13: =COUNTIFS(Restaurants!$F$3:$F$98,"$$",Restaurants!$AK$3:$AK$98,"Enriched") -> 22
A14: Belltown | B14: =COUNTIFS(Restaurants!$C$3:$C$98,"Belltown",Restaurants!$AK$3:$AK$98,"Enriched") -> 6 | D14: $$$ | E14: =COUNTIFS(Restaurants!$F$3:$F$98,"$$$",Restaurants!$AK$3:$AK$98,"Enriched") -> 35
A15: Fremont | B15: =COUNTIFS(Restaurants!$C$3:$C$98,"Fremont",Restaurants!$AK$3:$AK$98,"Enriched") -> 5 | D15: $$$$ | E15: =COUNTIFS(Restaurants!$F$3:$F$98,"$$$$",Restaurants!$AK$3:$AK$98,"Enriched") -> 7
A16: Downtown | B16: =COUNTIFS(Restaurants!$C$3:$C$98,"Downtown",Restaurants!$AK$3:$AK$98,"Enriched") -> 3
A17: Pike Place | B17: =COUNTIFS(Restaurants!$C$3:$C$98,"Pike Place",Restaurants!$AK$3:$AK$98,"Enriched") -> 6
A18: Queen Anne | B18: =COUNTIFS(Restaurants!$C$3:$C$98,"Queen Anne",Restaurants!$AK$3:$AK$98,"Enriched") -> 7 | D18: Live by Date-Night Score
A19: Wallingford | B19: =COUNTIFS(Restaurants!$C$3:$C$98,"Wallingford",Restaurants!$AK$3:$AK$98,"Enriched") -> 7 | D19: Score | E19: Live
A20: Madrona | B20: =COUNTIFS(Restaurants!$C$3:$C$98,"Madrona",Restaurants!$AK$3:$AK$98,"Enriched") -> 5 | D20: 5 | E20: =COUNTIFS(Restaurants!$U$3:$U$98,5,Restaurants!$AK$3:$AK$98,"Enriched") -> 7
A21: Madrona-adjacent | B21: =COUNTIFS(Restaurants!$C$3:$C$98,"Madrona-adjacent",Restaurants!$AK$3:$AK$98,"Enriched") -> 3 | D21: 4 | E21: =COUNTIFS(Restaurants!$U$3:$U$98,4,Restaurants!$AK$3:$AK$98,"Enriched") -> 33
A22: Phinney Ridge | B22: =COUNTIFS(Restaurants!$C$3:$C$98,"Phinney Ridge",Restaurants!$AK$3:$AK$98,"Enriched") -> 3 | D22: 3 | E22: =COUNTIFS(Restaurants!$U$3:$U$98,3,Restaurants!$AK$3:$AK$98,"Enriched") -> 21
A23: Greenwood | B23: =COUNTIFS(Restaurants!$C$3:$C$98,"Greenwood",Restaurants!$AK$3:$AK$98,"Enriched") -> 3 | D23: 2 | E23: =COUNTIFS(Restaurants!$U$3:$U$98,2,Restaurants!$AK$3:$AK$98,"Enriched") -> 10
A24: U District | B24: =COUNTIFS(Restaurants!$C$3:$C$98,"U District",Restaurants!$AK$3:$AK$98,"Enriched") -> 9

Sheet Restaurants
A1: SEED — you fill (min: Name, Neighborhood, URL) | H1: ENRICHMENT — Claude fills from websites + review/Google cross-check
A2: ID | B2: Restaurant Name * | C2: Neighborhood * | D2: Website URL * | E2: Cuisine (Primary) | F2: Price Tier | G2: Tags (your notes) | H2: Description | I2: Venue Type | J2: Address | K2: Phone | L2: Cuisine (Secondary) | M2: Dinner Hours | N2: Reservations | O2: Reservation Platform | P2: Vegetarian | Q2: Vegan | R2: Gluten-Free | S2: Ambiance Tags | T2: Noise Level | U2: Date-Night Score (1-5) | V2: Outdoor Seating | W2: Rating | X2: Rating Count | Y2: Review Snippet | Z2: Hero Dish 1 | AA2: Hero Dish 2 | AB2: Avg Entree Price | AC2: Menu URL | AD2: Menu Format | AE2: Menu File (local) | AF2: Photo URL | AG2: Latitude | AH2: Longitude | AI2: Menu Last Updated | AJ2: Verified Date | AK2: Enrichment Status
A3: 1 | B3: Spinasse | C3: Capitol Hill | D3: https://www.spinasse.com | E3: Italian | F3: $$$$ | G3: cozy;romantic;handmade-pasta | H3: Cascina Spinasse is Capitol Hill's temple to Piedmontese cooking, famous for tajarin — hand-cut egg pasta in butter and sage, almost translucent. The room is small, candlelit, and unapologetically romantic: the place you book when the night is supposed to matter. | I3: Restaurant | J3: 1531 14th Ave, Seattle, WA 98122 | K3: (206) 251-7673 | L3: Piedmontese | M3: Sun-Thu 5-10pm; Fri-Sat 5-11pm | N3: Yes | O3: Tock/Direct | P3: Y | Q3: N | R3: N | S3: Romantic; Candlelit; Intimate | T3: Moderate | U3: 5 | V3: N | X3: 1500+ | Y3: Award-winning Piemontese; hand-cut tajarin is the signature | Z3: Tajarin al burro e salvia | AA3: Agnolotti dal plin | AB3: $100+ a la carte | AC3: https://spinasse.com/menu/ | AD3: HTML | AI3: 2026-06 | AJ3: 2026-06-19 | AK3: Enriched
A4: 2 | B4: Artusi | C4: Capitol Hill | D4: https://www.artusibar.com | E4: Italian | F4: $$ | G4: cocktails;intimate | H4: Artusi is Spinasse's next-door aperitivo bar, grown into its own draw — negronis, Italian small plates, and a buzzy 21-and-over room. Walk in for a pre-dinner spritz or stay the night; it's flirtier and louder than its sibling, built for a date with momentum. | I4: Bar | J4: 1535 14th Ave, Seattle, WA 98122 | K4: (206) 678-8593 | L4: Aperitivo/Small plates | M4: Daily 5-10pm (Fri-Sat to 11) | N4: Walk-in | O4: Walk-in (res 3+) | P4: Y | Q4: N | R4: Y | S4: Lively; Stylish; Date-friendly | T4: Loud | U4: 4 | V4: N | X4: 350+ | Y4: Spinasse's aperitivo bar; cocktails + Italian snacks, 21+ | Z4: Negroni | AA4: Seasonal cicchetti | AB4: $25-40 | AC4: https://artusibar.com/ | AD4: HTML | AI4: 2026-06 | AJ4: 2026-06-19 | AK4: Enriched
A5: 3 | B5: Taurus Ox | C5: Capitol Hill | D5: https://www.taurusox.com | E5: Laotian | F5: $$ | G5: spicy;hip | H5: Taurus Ox brings Laotian cooking rarely found in Seattle to a petite Capitol Hill room — fermented, herbal, chili-bright. Lao sausage, braised pork-belly thom khem, a cult Lao burger. No reservations and a little tight on tables; right for a casual, adventurous date. | I5: Restaurant | J5: 903 19th Ave E, Seattle, WA 98112 | K5: (206) 466-2785 | L5: Laotian | M5: Tue-Sat 11-2pm & 5-9pm | N5: Walk-in | O5: Waitlist at door | P5: Y | Q5: Y | R5: Y | S5: Hip; Cozy; Casual | T5: Moderate | U5: 3 | V5: N | X5: 590+ | Y5: Rare Laotian menu; Lao sausage and thom khem are standouts | Z5: Lao sausage | AA5: Thom khem (braised pork belly) | AB5: $15-25 | AC5: https://www.taurusox.com/ | AD5: HTML | AI5: 2026-06 | AJ5: 2026-06-19 | AK5: Enriched
A6: 4 | B6: Momiji | C6: Capitol Hill | D6: https://www.momijiseattle.com | E6: Japanese/Sushi | F6: $$$ | G6: garden;cozy | H6: Momiji hides a serene courtyard garden behind a busy Capitol Hill block — the rare sushi room that feels like an escape. Order omakase or work the roll list; the back patio under string lights is one of the neighborhood's quietly romantic seats. Open late for a spontaneous night. | I6: Restaurant | J6: 1522 12th Ave, Seattle, WA 98122 | K6: (206) 457-4068 | L6: Sushi/Omakase | M6: Daily 4pm-12am | N6: Yes | O6: OpenTable | P6: Y | Q6: N | R6: Y | S6: Garden patio; Cozy; Romantic | T6: Moderate | U6: 4 | V6: Y | X6: 2000+ | Y6: Sushi & omakase around a hidden courtyard garden | Z6: Omakase | AA6: Capitol Hill Roll | AB6: $30-50 | AC6: https://www.momijiseattle.com/ | AD6: HTML | AI6: 2026-06 | AJ6: 2026-06-19 | AK6: Enriched
A7: 5 | B7: Terra Plata | C7: Capitol Hill | D7: https://www.terraplata.com | E7: Pacific NW | F7: $$$ | G7: rooftop;seasonal | H7: Terra Plata is Tamara Murphy's earth-to-plate room crowned by a covered, heated rooftop garden — greenery, herbs, and one of Capitol Hill's best al-fresco perches. The menu shifts with the season and leans Mediterranean; Monday paella night is the local ritual. Book the roof when weather turns. | I7: Restaurant | J7: 1501 Melrose Ave, Seattle, WA 98122 | K7: (206) 325-1501 | L7: Farm-to-table/Mediterranean | M7: Mon-Fri 4-10pm; Sat 9:30am-10pm; Sun 9:30am-9pm | N7: Yes | O7: OpenTable | P7: Y | Q7: Y | R7: Y | S7: Rooftop garden; Charming; Seasonal | T7: Moderate | U7: 4 | V7: Y | X7: 1300+ | Y7: James Beard chef Tamara Murphy; rooftop garden, Monday paella | Z7: Paella (Mon night) | AA7: Seasonal market plates | AB7: $30-50 | AC7: https://www.terraplata.com/ | AD7: HTML | AI7: 2026-06 | AJ7: 2026-06-19 | AK7: Enriched
A8: 6 | B8: Rione XIII | C8: Capitol Hill | D8: https://www.ethanstowellrestaurants.com | E8: Italian | F8: $$$ | G8: neighborhood;wine | H8: Rione XIII channels Rome's Trastevere on 15th Ave — fried artichokes, cacio e pepe, carbonara, and blistered Roman pizza, with a wine list to match. It's the Ethan Stowell room that feels most like a neighborhood trattoria: lively, warm, and easy to linger in. Reservations smooth the wait. | I8: Restaurant | J8: 401 15th Ave E, Seattle, WA 98112 | K8: (206) 838-2878 | L8: Roman | M8: Daily 5-10pm | N8: Yes | O8: OpenTable | P8: Y | Q8: N | R8: N | S8: Neighborhood; Warm; Wine-focused | T8: Moderate | U8: 4 | V8: N | X8: 490+ | Y8: Roman cuisine & wood-fired pizza, Ethan Stowell trattoria | Z8: Cacio e pepe | AA8: Roman-style pizza | AB8: $30-45 | AC8: https://ethanstowellrestaurants.com/restaurants/rione-xiii-capitol-hill-seattle | AD8: HTML | AI8: 2026-06 | AJ8: 2026-06-19 | AK8: Enriched
A9: 7 | B9: Altura | C9: Capitol Hill | D9: https://www.alturarestaurant.com | E9: Italian Tasting Menu | F9: $$$$ | G9: tasting-menu;special-occasion | H9: Altura is Capitol Hill's special-occasion summit — Nathan Lockwood's weekly-changing Italian-Pacific Northwest tasting menu in a hushed, candlelit room over a long, unhurried evening. At $137 a person it's a commitment, and the kind of night you book when the occasion deserves one. Reserve directly. | I9: Restaurant | J9: 617 Broadway E, Seattle, WA 98102 | K9: (206) 402-6749 | L9: Italian-PNW tasting | M9: Tue-Thu 5:30-10pm; Fri-Sat 5-10pm | N9: Yes | O9: Direct (not OpenTable) | P9: Y | Q9: N | R9: Y | S9: Romantic; Hushed; Special-occasion | T9: Quiet | U9: 5 | V9: N | X9: 700+ | Y9: Weekly-changing Italian-PNW tasting menu, $137pp | Z9: Chef's tasting menu | AA9: Handmade pasta course | AB9: $137 prix fixe | AC9: https://alturarestaurant.com/ | AD9: HTML | AI9: 2026-06 | AJ9: 2026-06-19 | AK9: Enriched
A10: 8 | B10: Jeffry's (formerly Bateau) | C10: Capitol Hill | D10: https://www.sea-creatures.com/ | E10: Steakhouse | F10: $$$ | G10: craft-butchery;romantic | H10: Jeffry's is the 2026 reboot of Renee Erickson's beloved Bateau — same in-house dry-aged beef, leaner and more approachable, with a 'Humble Cuts' menu of lesser-known cuts. The intimate Union St room still reads like a date-night steakhouse, just with a friendlier check. Wednesday through Sunday only. | I10: Restaurant | J10: 1040 E Union St, Seattle, WA 98122 | K10: (206) 900-8699 | L10: Dry-aged steakhouse | M10: Wed-Sun 5-9pm | N10: Yes | O10: Resy | P10: N | Q10: N | R10: Y | S10: Intimate; Romantic; Refined | T10: Moderate | U10: 4 | V10: N | X10: 430+ | Y10: Renee Erickson dry-aged steakhouse, reopened 2026 as Jeffry's | Z10: Dry-aged steak | AA10: Humble Cuts selection | AB10: $45-70 | AC10: https://www.sea-creatures.com/ | AD10: HTML | AI10: 2026-06 | AJ10: 2026-06-19 | AK10: Enriched
A11: 9 | B11: Stateside | C11: Capitol Hill | D11: https://www.statesideseattle.com | E11: Vietnamese-French | G11: bright;date-friendly | I11: Restaurant | AK11: CLOSED - drop
A12: 10 | B12: Witness | C12: Capitol Hill | D12: https://www.witnessbar.com | E12: Southern | G12: cocktails;intimate | I12: Restaurant | AK12: CLOSED - drop
A13: 11 | B13: San Fermo | C13: Ballard | D13: https://www.sanfermo.com | E13: Italian | F13: $$$ | G13: cozy;romantic | H13: San Fermo is a candlelit cottage on Ballard Ave doing rustic, ingredient-driven Italian — handmade pasta like strozzapreti amatriciana, burrata to start, olive oil cake to finish. The old house feels intimate and a little hidden, the kind of cozy that makes a two-top feel like the only table. Reserve ahead. | I13: Restaurant | J13: 5341 Ballard Ave NW, Seattle, WA 98107 | K13: (206) 342-1530 | L13: Northern Italian | M13: Daily 5-10pm | N13: Yes | O13: OpenTable | P13: Y | Q13: N | R13: N | S13: Cozy; Candlelit; Romantic | T13: Moderate | U13: 4 | V13: N | X13: 670+ | Y13: Cozy Ballard Ave Italian; handmade pasta, local ingredients | Z13: Strozzapreti amatriciana | AA13: Burrata | AB13: $25-40 | AC13: https://www.sanfermo.com | AD13: HTML | AI13: 2026-06 | AJ13: 2026-06-19 | AK13: Enriched
A14: 12 | B14: The Walrus and the Carpenter | C14: Ballard | D14: https://www.thewalrusbar.com | E14: Seafood | F14: $$$ | G14: oysters;intimate | H14: The Walrus and the Carpenter is Renee Erickson's iconic oyster bar — a tiny, candlelit room where the night is built around freshly shucked oysters, steak tartare, and crisp wine. First-come only and always a little buzzy; arrive early and let a date unfold over a tower of ice and a bottle of Muscadet. | I14: Restaurant | J14: 4743 Ballard Ave NW, Seattle, WA 98107 | K14: (206) 395-9227 | L14: Oyster/Raw bar | M14: Sun-Thu 4-9pm; Fri-Sat 4-10pm | N14: Walk-in | O14: First-come, no res | P14: Y | Q14: N | R14: Y | S14: Intimate; Buzzy; Romantic | T14: Loud | U14: 4 | V14: N | X14: 2000+ | Y14: Renee Erickson's celebrated oyster bar; tiny and lively | Z14: Fresh oysters | AA14: Steak tartare | AB14: $40-60 | AC14: https://thewalrusbar.com | AD14: HTML | AI14: 2026-06 | AJ14: 2026-06-19 | AK14: Enriched
A15: 13 | B15: Stoneburner | C15: Ballard | D15: https://www.stoneburnerseattle.com | E15: Italian | F15: $$$ | G15: wood-fired;warm | H15: Stoneburner pairs rustic Italian technique with Pacific Northwest ingredients inside Hotel Ballard — wood-fired vegetables, handmade pasta, blistered pizza in a warm, high-ceilinged room. It's lively without being loud and easy to book, a dependable date that works for a casual Tuesday or a dressed-up Saturday alike. | I15: Restaurant | J15: 5214 Ballard Ave NW, Seattle, WA 98107 | K15: (206) 695-2051 | L15: Italian-PNW; wood-fired | M15: Wed-Sat 4:30-9pm; Sun brunch + 4:30-9pm | N15: Yes | O15: OpenTable | P15: Y | Q15: Y | R15: Y | S15: Warm; Wood-fired; Easy | T15: Moderate | U15: 4 | V15: N | X15: 830+ | Y15: Rustic Italian + PNW in Hotel Ballard; handmade pasta | Z15: Handmade pasta | AA15: Wood-fired pizza | AB15: $25-40 | AC15: https://www.stoneburnerseattle.com/menu | AD15: HTML | AI15: 2026-06 | AJ15: 2026-06-19 | AK15: Enriched
A16: 14 | B16: Bastille Café | C16: Ballard | D16: https://www.bastilleseattle.com | E16: French | G16: patio;romantic | I16: Restaurant | Y16: Closed — space now Sabine Café (possible swap) | AJ16: 2026-06-19 | AK16: CLOSED - drop
A17: 15 | B17: La Carta de Oaxaca | C17: Ballard | D17: https://www.lacartadeoaxaca.com | E17: Mexican | F17: $$ | G17: lively;authentic | H17: La Carta de Oaxaca has anchored Ballard Ave since 2003 with the city's benchmark mole negro, handmade tortillas, and mezcal. It's lively, family-run, and walk-in only, so expect a wait at the bar — part of the charm. A spirited, unfussy date over shared plates and a good cocktail. | I17: Restaurant | J17: 5431 Ballard Ave NW, Seattle, WA 98107 | K17: (206) 782-8722 | L17: Oaxacan | M17: Tue-Thu 11:30am-9:30pm; Fri-Sat to 10:30pm | N17: Walk-in | O17: No res (popular) | P17: Y | Q17: Y | R17: Y | S17: Lively; Authentic; Festive | T17: Loud | U17: 3 | V17: N | X17: 1400+ | Y17: Benchmark Oaxacan; famous mole negro, walk-in only | Z17: Mole negro | AA17: Tacos al pastor | AB17: $15-25 | AC17: https://seattlemeetsoaxaca.com | AD17: HTML | AI17: 2026-06 | AJ17: 2026-06-19 | AK17: Enriched
A18: 16 | B18: Ruam Mit Thai | C18: Ballard | D18: https://www.ruammitthai.com | E18: Thai | G18: casual-date | I18: Restaurant | Y18: Not found in Ballard — verify/likely closed | AJ18: 2026-06-19 | AK18: CLOSED - drop
A19: 17 | B19: Sawyer | C19: Ballard | D19: https://www.sawyerseattle.com | E19: American | G19: creative;fun | I19: Restaurant | Y19: Closed (2026) | AJ19: 2026-06-19 | AK19: CLOSED - drop
A20: 18 | B20: The Ballard Cut | C20: Ballard | D20: https://www.ballardcut.com | E20: Steakhouse | F20: $$$ | G20: whiskey;intimate | H20: The Ballard Cut is a moody steakhouse-meets-whiskey-bar with a 1,200-bottle list — tomahawks, aged New York strip, and a sleeper-hit spicy arrabbiata. Low light, dark wood, and a serious pour make it a grown-up date: order a dry-aged cut, let someone walk you through the rye, and settle in. | I20: Restaurant | J20: 2221 NW Market St, Seattle, WA 98107 | K20: (564) 654-3008 | L20: Steakhouse/New American; whiskey bar | M20: Mon-Thu 4-10pm; Fri-Sat 4-11pm; Sun 4-9pm | N20: Yes | O20: OpenTable | P20: N | Q20: N | R20: Y | S20: Moody; Whiskey; Intimate | T20: Moderate | U20: 4 | V20: N | X20: 320+ | Y20: Steakhouse + 1,200-bottle whiskey bar; tomahawk, aged strip | Z20: Aged New York strip | AA20: Spicy arrabbiata | AB20: $35-60 | AC20: https://theballardcut.com/menu/ | AD20: HTML | AI20: 2026-06 | AJ20: 2026-06-19 | AK20: Enriched
A21: 19 | B21: Ocho | C21: Ballard | D21: https://www.ochoseattle.com | E21: Spanish | F21: $$ | G21: tapas;romantic | H21: Ocho is a tiny Ballard tapas bar built for grazing — patatas bravas, tortilla española, sherried mushrooms on toast, and a deep bench of Spanish wine and sherry. No reservations and elbow-to-elbow, which is exactly why it works for a date: order a dozen small things, share everything, stay late. | I21: Bar | J21: 2325 NW Market St, Seattle, WA 98107 | K21: (206) 784-0699 | L21: Spanish tapas | M21: Daily, dinner to late (to 2am) | N21: Walk-in | O21: No res (text-when-ready) | P21: Y | Q21: Y | R21: Y | S21: Tiny; Romantic; Late-night | T21: Loud | U21: 4 | V21: Y | X21: 680+ | Y21: Tiny Spanish tapas + sherry bar; grazing, no reservations | Z21: Patatas bravas | AA21: Tortilla española | AB21: $15-30 | AC21: https://www.ochoseattle.com | AD21: HTML | AI21: 2026-06 | AJ21: 2026-06-19 | AK21: Enriched
A22: 20 | B22: Shiro's | C22: Belltown | D22: https://www.shiros.com | E22: Japanese/Sushi | F22: $$$$ | G22: classic;chef-driven | H22: Shiro's is Seattle's Edomae sushi institution, founded by the master who put the city's raw-fish scene on the map. Sit at the bar for omakase and watch each piece set down one at a time. Spare, classic, and serious about fish — a refined date for two who'd rather talk over nigiri than noise. | I22: Restaurant | J22: 2401 2nd Ave, Seattle, WA 98121 | K22: (206) 443-9844 | L22: Edomae sushi/Omakase | M22: Daily 4:30-9pm (Fri-Sun to 9:30) | N22: Yes | O22: Resy | P22: N | Q22: N | R22: Y | S22: Classic; Chef-driven; Refined | T22: Quiet | U22: 4 | V22: N | X22: 2800+ | Y22: Seattle's original Edomae sushi; omakase $140, chef's choice $85 | Z22: Omakase | AA22: Nigiri sushi course | AB22: $85-140 omakase | AC22: https://shiros.com/ | AD22: HTML | AI22: 2026-06 | AJ22: 2026-06-19 | AK22: Enriched
A23: 21 | B23: El Gaucho | C23: Belltown | D23: https://www.elgaucho.com | E23: Steakhouse | F23: $$$$ | G23: classic;music | H23: El Gaucho is old-school supper-club theater — tuxedoed servers, tableside Caesar and bananas Foster, 28-day dry-aged beef over a charcoal grill, often a piano in the background. It's a splurge built for an occasion; book a booth, dress up, and lean into the romance of a steakhouse that still performs. | I23: Restaurant | J23: 2200 Western Ave Ste 101, Seattle, WA 98121 | K23: (206) 728-1337 | L23: Dry-aged steakhouse | M23: Tue-Sat 4pm-late (to 9:30/10pm) | N23: Yes | O23: SevenRooms | P23: N | Q23: N | R23: Y | S23: Classic; Theatrical; Special-occasion | T23: Moderate | U23: 5 | V23: N | X23: 1490+ | Y23: Old-school supper club; tableside service, dry-aged beef | Z23: Steak El Gaucho (filet + lobster) | AA23: Bananas Foster (tableside) | AB23: $55-90 | AC23: https://elgaucho.com/seattle/ | AD23: HTML | AI23: 2026-06 | AJ23: 2026-06-19 | AK23: Enriched
A24: 22 | B24: List | C24: Belltown | D24: https://www.listbelltown.com | E24: Italian | G24: small-plates;sexy | I24: Restaurant | Y24: Yelp shows CLOSED (May 2026); OpenTable still lists — verify before include | AJ24: 2026-06-19 | AK24: Review
A25: 23 | B25: Tilikum Place Café | C25: Belltown | D25: https://www.tilikumplacecafe.com | E25: European | F25: $$$ | G25: cozy;brunch-date | H25: Tilikum Place Café is a tucked-away little room by the Chief Sealth fountain, beloved for its giant Dutch baby pancake but quietly excellent at dinner — a short, seasonal European-leaning menu in a warm, intimate space. Dinner runs Thursday through Saturday only, so landing a table feels like a small secret. | I25: Restaurant | J25: 407 Cedar St, Seattle, WA 98121 | K25: (206) 282-4830 | L25: European/New American | M25: Dinner Thu-Sat 5-9pm; weekend brunch | N25: Yes | O25: OpenTable | P25: Y | Q25: N | R25: Y | S25: Cozy; Charming; Intimate | T25: Quiet | U25: 4 | V25: N | X25: 2400+ | Y25: Tucked-away bistro; famed Dutch baby, limited dinner nights | Z25: Seared halibut | AA25: Dutch baby (brunch) | AB25: $25-40 | AC25: https://www.tilikumplacecafe.com/menus | AD25: HTML | AI25: 2026-06 | AJ25: 2026-06-19 | AK25: Enriched
A26: 24 | B26: Umi Sake House | C26: Belltown | D26: https://www.umisakehouse.com | E26: Japanese/Sushi | F26: $$$ | G26: loungey;late-night | H26: Umi Sake House is a buzzy Belltown izakaya — a sprawling sushi list, 60-plus sakes, and a hidden tropical back patio that's the seat to request. It's loud, fun, and open late, the kind of high-energy date where you order too many rolls, work through the sake menu, and stay longer than planned. | I26: Restaurant | J26: 2230 1st Ave, Seattle, WA 98121 | K26: (206) 374-8717 | L26: Izakaya/Sushi | M26: Daily 4pm-11pm (Fri-Sat to 12am) | N26: Yes | O26: OpenTable | P26: Y | Q26: Y | R26: Y | S26: Loungey; Late-night; Buzzy | T26: Loud | U26: 3 | V26: Y | X26: 4300+ | Y26: Big izakaya sushi menu, 60+ sakes, tropical back patio | Z26: Specialty rolls | AA26: Izakaya small plates | AB26: $25-45 | AC26: https://www.umisakehouse.com/menus | AD26: HTML | AI26: 2026-06 | AJ26: 2026-06-19 | AK26: Enriched
A27: 25 | B27: Shaker + Spear | C27: Belltown | D27: https://www.shakerandspear.com | E27: Seafood | F27: $$$ | G27: modern;hotel-date | H27: Shaker + Spear is a polished, market-driven seafood room inside the Kimpton Palladian — Northwest fish, seasonal plates, and a cocktail list worth lingering over in a handsome 1910 building. It's a calm, grown-up hotel-restaurant date: easy to book, quietly stylish, and reliably good without the wait of Ballard's oyster bars. | I27: Restaurant | J27: 2000 2nd Ave, Seattle, WA 98121 | K27: (206) 826-1700 | L27: Pacific NW seafood | M27: Dinner daily 4:45-9pm | N27: Yes | O27: OpenTable | P27: Y | Q27: N | R27: Y | S27: Modern; Polished; Hotel-date | T27: Moderate | U27: 4 | V27: N | X27: 1240+ | Y27: Market-driven NW seafood in the Kimpton Palladian | Z27: Seasonal whole fish | AA27: Seafood tower | AB27: $30-50 | AC27: https://shakerandspear.com/menus | AD27: HTML | AI27: 2026-06 | AJ27: 2026-06-19 | AK27: Enriched
A28: 26 | B28: Local 360 | C28: Belltown | D28: https://www.local360.org | E28: American | G28: farm-to-table | I28: Restaurant | Y28: Closed (2026) | AJ28: 2026-06-19 | AK28: CLOSED - drop
A29: 27 | B29: Black Bottle | C29: Belltown | D29: https://www.blackbottleseattle.com | E29: Gastropub | F29: $$ | G29: lively;shareable | H29: Black Bottle calls itself Seattle's first gastropub — a 21-plus Belltown gastrotavern of shareable plates and craft cocktails: smoked wild boar ribs, bacon-lemon scallops, Spanish-fried olives. Unfussy, lively, and easy on the wallet, it's a low-stakes date that rewards ordering a stack of small plates and a couple of stiff drinks. | I29: Restaurant | J29: 2600 1st Ave, Seattle, WA 98121 | K29: (206) 441-1500 | L29: Gastropub/shared plates | M29: Mon-Sat 4-10pm (Fri-Sat to 11); Sun closed | N29: Yes | O29: OpenTable | P29: Y | Q29: Y | R29: Y | S29: Lively; Shareable; Casual | T29: Loud | U29: 3 | V29: Y | X29: 1220+ | Y29: Seattle's first gastropub; shareable plates, 21+ | Z29: Smoked wild boar ribs | AA29: Bacon-lemon scallops | AB29: $15-30 | AC29: https://www.blackbottleseattle.com/ | AD29: HTML | AI29: 2026-06 | AJ29: 2026-06-19 | AK29: Enriched
A30: 28 | B30: Rob Roy | C30: Belltown | D30: https://www.robroyseattle.com | E30: Cocktail Bar | G30: dark;romantic | I30: Bar | Y30: Cocktail bar, no kitchen (only bar snacks) — exclude per dinner-only rule | AJ30: 2026-06-19 | AK30: Review
A31: 29 | B31: Revel | C31: Fremont | D31: https://www.revelseattle.com | E31: Korean-Fusion | F31: $$ | G31: fun;creative | H31: Revel is Fremont's modern Korean kitchen — short-rib dumplings, scallion-and-kimchi pancakes, and rice and noodle bowls off a menu that turns over monthly. The room is communal and energetic with a sharp cocktail bar attached, a lively, creative date where the food is adventurous but the vibe stays easygoing. | I31: Restaurant | J31: 401 N 36th St, Seattle, WA 98103 | K31: (206) 547-2040 | L31: Korean-American | M31: Tue-Sun 5-9pm (Fri-Sat to 10) | N31: Yes | O31: OpenTable | P31: Y | Q31: Y | R31: Y | S31: Creative; Communal; Energetic | T31: Loud | U31: 4 | V31: Y | X31: 1500+ | Y31: Modern Korean small plates, monthly menu, cocktail bar | Z31: Kimchi-scallion pancake | AA31: Short rib dumplings | AB31: $18-30 | AC31: https://www.revelseattle.com | AD31: HTML | AI31: 2026-06 | AJ31: 2026-06-19 | AK31: Enriched
A32: 30 | B32: Le Coin | C32: Fremont | D32: https://www.lecoinseattle.com | E32: French | F32: $$$ | G32: romantic;neighborhood | H32: Le Coin turned the old Buckaroo Tavern into a buzzy French-leaning bistro — Northwest seafood and game, a great caviar service, and Brussels sprouts people cross town for. Romantic without being stiff, the kind of neighborhood spot that feels like an occasion. Reservations drop on the 15th for the next month, so plan ahead. | I32: Restaurant | J32: 4201 Fremont Ave N, Seattle, WA 98103 | K32: (206) 708-7207 | L32: French/PNW seafood | M32: Dinner nightly 4-9pm (Fri-Sat to 10); brunch Thu-Sun | N32: Yes | O32: Tock | P32: Y | Q32: N | R32: Y | S32: Romantic; Neighborhood-chic; Lively | T32: Moderate | U32: 4 | V32: N | X32: 640+ | Y32: French bistro in old Buckaroo Tavern; caviar, game, seafood | Z32: Caviar service | AA32: Crispy Brussels sprouts | AB32: $30-50 | AC32: https://lecoinseattle.com/ | AD32: HTML | AI32: 2026-06 | AJ32: 2026-06-19 | AK32: Enriched
A33: 31 | B33: Pomerol | C33: Fremont | D33: https://www.pomerolrestaurant.com | E33: French | G33: wood-fired;intimate | I33: Restaurant | Y33: Closed (2026) — space now Meesha 127 (Indian) | AJ33: 2026-06-19 | AK33: CLOSED - drop
A34: 32 | B34: RockCreek | C34: Fremont | D34: https://www.rockcreekseattle.com | E34: Seafood | F34: $$$ | G34: cozy;date-night | H34: RockCreek is a soaring A-frame packed with globally sourced fish — Northwest oysters and crab alongside Hawaiian ono and East Coast striped bass, all arriving daily. Warm, a little loud, and consistently excellent, the reliable Fremont seafood date when you want range beyond the usual oysters and a deep cocktail list. | I34: Restaurant | J34: 4300 Fremont Ave N, Seattle, WA 98103 | K34: (206) 557-7532 | L34: Global seafood | M34: Mon-Fri 4-10pm; Sat-Sun 10am-10pm | N34: Yes | O34: OpenTable | P34: Y | Q34: N | R34: Y | S34: Cozy; Bustling; Date-night | T34: Loud | U34: 4 | V34: Y | X34: 1360+ | Y34: Two-story A-frame; globally sourced fish, daily fresh | Z34: Oysters & shellfish | AA34: Daily fresh fish | AB34: $25-45 | AC34: https://rockcreekseafood.com/seattle-menu/ | AD34: HTML | AI34: 2026-06 | AJ34: 2026-06-19 | AK34: Enriched
A35: 33 | B35: Manolin | C35: Fremont | D35: https://www.manolinseattle.com | E35: Seafood | G35: tropical;bar | I35: Restaurant | Y35: Closed (2026) — now Old Salt Fish & Bagel | AJ35: 2026-06-19 | AK35: CLOSED - drop
A36: 34 | B36: Paseo | C36: Fremont | D36: https://www.paseorestaurants.com | E36: Caribbean | F36: $ | G36: casual-date | H36: Paseo is a Seattle rite of passage — Caribbean sandwiches piled with caramelized onions and slow-roasted pork that inspire citywide devotion. It's a counter-service hole-in-the-wall, not a sit-down affair, but for a casual, messy, deeply happy date over the famous Caribbean Roast, few things beat it. | I36: Restaurant | J36: 4225 Fremont Ave N, Seattle, WA 98103 | K36: (206) 545-7440 | L36: Caribbean sandwiches | M36: Tue-Fri 11am-9pm; Sat to 8; Sun/Mon to 6 | N36: No | O36: Counter service | P36: Y | Q36: N | R36: N | S36: Casual; Iconic; No-frills | T36: Moderate | U36: 2 | V36: Y | X36: 5600+ | Y36: Cult Caribbean sandwich counter; the Caribbean Roast | Z36: Caribbean Roast sandwich | AA36: Pork platos | AB36: $12-18 | AC36: https://www.paseo.com/menu | AD36: HTML | AI36: 2026-06 | AJ36: 2026-06-19 | AK36: Enriched
A37: 35 | B37: Agrodolce | C37: Fremont | D37: https://www.agrodolceseattle.com | E37: Italian | G37: organic;romantic | I37: Restaurant | Y37: Yelp shows CLOSED (Feb 2026); verify before include | AJ37: 2026-06-19 | AK37: Review
A38: 36 | B38: Red Star Taco Bar | C38: Fremont | D38: https://www.redstartacobar.com | E38: Mexican | F38: $$ | G38: casual;fun | H38: Red Star Taco Bar is a 21-plus Fremont taqueria built around eclectic tacos and a serious tequila and frozen-margarita program — carnitas next to Korean BBQ and Bang Bang cauliflower. Loud, fun, and open late, an unpretentious date for two who'd rather split a dozen tacos and a pitcher than dress up. | I38: Restaurant | J38: 513 N 36th St Ste E, Seattle, WA 98103 | K38: (206) 471-5027 | L38: Tacos/Tequila | M38: Sun-Thu 11am-12am; Fri-Sat to 2am | N38: Walk-in | O38: Walk-in (21+) | P38: Y | Q38: Y | R38: Y | S38: Fun; Casual; Late-night | T38: Loud | U38: 3 | V38: Y | X38: 530+ | Y38: Eclectic tacos + tequila, 21+, late-night | Z38: Carnitas tacos | AA38: Frozen margarita | AB38: $12-22 | AC38: https://www.redstartacobar.com/ | AD38: HTML | AI38: 2026-06 | AJ38: 2026-06-19 | AK38: Enriched
A39: 37 | B39: Fiasco | C39: Fremont | D39: https://www.fiascoseattle.com | E39: Italian | G39: neighborhood;wine | I39: Restaurant | Y39: Yelp shows CLOSED (Dec 2025); verify before include | AJ39: 2026-06-19 | AK39: Review
A40: 38 | B40: The Whale Wins | C40: Fremont | D40: https://www.thewhalewins.com | E40: Pacific NW | G40: bright;seasonal | I40: Restaurant | Y40: Permanently closed Oct 2025 | AJ40: 2026-06-19 | AK40: CLOSED - drop
A41: 39 | B41: The Capital Grille | C41: Downtown | D41: https://www.thecapitalgrille.com | E41: Steakhouse | F41: $$$$ | G41: classic;special-occasion | H41: The Capital Grille is the polished, clubby steakhouse downtown leans on for occasions — dry-aged steaks hand-cut in house, a 350-label wine list, and dark-wood booths made for lingering. It's a chain, but a serious one; for a dressed-up date or a celebration near the theaters, it delivers exactly what it promises. | I41: Restaurant | J41: 1301 4th Ave, Seattle, WA 98101 | K41: (206) 382-0900 | L41: Dry-aged steakhouse | M41: Mon-Thu 5-10pm; Fri-Sat 4:30-11pm; Sun 4-9pm | N41: Yes | O41: OpenTable | P41: Y | Q41: N | R41: Y | S41: Clubby; Classic; Special-occasion | T41: Moderate | U41: 4 | V41: N | X41: 1300+ | Y41: Upscale steakhouse; in-house dry-aged beef, 350-label wine list | Z41: Dry-aged bone-in ribeye | AA41: Lobster mac & cheese | AB41: $45-75 | AC41: https://www.thecapitalgrille.com/menu | AD41: HTML | AI41: 2026-06 | AJ41: 2026-06-19 | AK41: Enriched
A42: 40 | B42: The George (formerly The Georgian) | C42: Downtown | D42: https://www.thegeorgeseattle.com/ | E42: Pacific NW/American | F42: $$$$ | G42: grand;romantic | H42: The George - the reborn Georgian inside the Fairmont Olympic - is the grandest room downtown, all soaring ceilings and chandeliers, now an American brasserie of local seafood, handmade pasta, and signature cuts. It's pure old-world occasion: book it for an anniversary, dress the part, and let the ballroom grandeur do the romancing. | I42: Restaurant | J42: 411 University St, Seattle, WA 98101 | K42: (206) 621-7889 | L42: American brasserie | M42: Mon, Thu, Sun 5-9pm; Fri-Sat 5-9:30pm | N42: Yes | O42: OpenTable | P42: Y | Q42: N | R42: Y | S42: Grand; Opulent; Romantic | T42: Moderate | U42: 5 | V42: N | X42: 280+ | Y42: Grand Fairmont brasserie (renamed from The Georgian) | Z42: Local seafood | AA42: Handmade pasta | AB42: $40-65 | AC42: https://www.thegeorgeseattle.com/ | AD42: HTML | AI42: 2026-06 | AJ42: 2026-06-19 | AK42: Enriched
A43: 41 | B43: Purple Café | C43: Downtown | D43: https://www.thepurplecafe.com | E43: American | F43: $$$ | G43: wine;date-night | H43: Purple Café is built around a four-story spiral wine tower - a downtown wine bar and New American kitchen with a list deep enough to make choosing the evening's bottle the main event. Handsome and central, easy for a pre-theater or after-work date where the wine leads and the shared plates keep pace. | I43: Restaurant | J43: 1225 4th Ave, Seattle, WA 98101 | K43: (206) 829-2280 | L43: Wine bar | M43: Mon-Fri to 9-10pm; Sat-Sun to 9-10pm | N43: Yes | O43: OpenTable | P43: Y | Q43: Y | R43: Y | S43: Wine-focused; Lively; Central | T43: Moderate | U43: 3 | V43: N | X43: 3000+ | Y43: Four-story wine tower; New American wine bar (verify summer hours) | Z43: Cheese & charcuterie | AA43: Seasonal entrees | AB43: $25-45 | AC43: https://www.purplecafe.com/seattle/ | AD43: HTML | AI43: 2026-06 | AJ43: 2026-06-19 | AK43: Enriched
A44: 42 | B44: Café Campagne | C44: Pike Place | D44: https://www.cafecampagne.com | E44: French | F44: $$$ | G44: romantic;classic | H44: Café Campagne has been Seattle's classic French bistro since 1994, tucked into Post Alley below the Market bustle - steak frites, escargot, a proper apero hour, and the kind of unhurried Gallic warmth that makes a table feel like Paris. Reliably romantic, especially in the early evening before the crowds. | I44: Restaurant | J44: 1600 Post Alley, Seattle, WA 98101 | K44: (206) 728-2233 | L44: French bistro | M44: Dinner nightly 5-9pm (Sun to 8) | N44: Yes | O44: OpenTable | P44: Y | Q44: N | R44: N | S44: Romantic; Classic; Parisian | T44: Moderate | U44: 4 | V44: N | X44: 1380+ | Y44: Classic Post Alley French bistro since 1994 | Z44: Steak frites | AA44: Escargot | AB44: $28-45 | AC44: https://cafecampagne.com/menu | AD44: HTML | AI44: 2026-06 | AJ44: 2026-06-19 | AK44: Enriched
A45: 43 | B45: Matt’s in the Market | C45: Pike Place | D45: https://www.mattsinthemarket.com | E45: Pacific NW | F45: $$$ | G45: market-view;romantic | H45: Matt's in the Market is the insider's Pike Place room - a small, light-filled space overlooking the Market clock, serving Northwest seafood that changes with the day's catch. Intimate and unfussy, the kind of place locals send out-of-towners and then quietly keep for their own date nights. Book the window. | I45: Restaurant | J45: 94 Pike St Ste 32, Seattle, WA 98101 | K45: (206) 467-7909 | L45: Pacific NW seafood | M45: Dinner nightly 5:30-10pm | N45: Yes | O45: OpenTable | P45: Y | Q45: N | R45: Y | S45: Market-view; Intimate; Romantic | T45: Moderate | U45: 4 | V45: N | X45: 1210+ | Y45: Insider Pike Place seafood with Market clock views | Z45: Seafood stew | AA45: Seasonal fresh fish | AB45: $30-50 | AC45: https://www.mattsinthemarket.com | AD45: HTML | AI45: 2026-06 | AJ45: 2026-06-19 | AK45: Enriched
A46: 44 | B46: The Pink Door | C46: Pike Place | D46: https://www.thepinkdoor.net | E46: Italian-American | F46: $$$ | G46: cabaret;romantic | H46: The Pink Door is Seattle's theatrical Italian institution - no sign, just a pink door off Post Alley opening onto pasta, Elliott Bay views from the deck, and live cabaret, trapeze, and tarot most nights. Romantic and a little bit circus, an unforgettable date when you want dinner to come with a show. | I46: Restaurant | J46: 1919 Post Alley, Seattle, WA 98101 | K46: (206) 443-3241 | L46: Italian-American | M46: Tue-Sat 11:30am-11:30pm; Sun-Mon closed | N46: Yes | O46: Tock | P46: Y | Q46: N | R46: Y | S46: Theatrical; Romantic; Iconic | T46: Loud | U46: 5 | V46: Y | X46: 8000+ | Y46: Hidden Italian with cabaret, trapeze, and bay-view deck | Z46: Linguine alle vongole | AA46: Lasagna | AB46: $28-45 | AC46: https://www.thepinkdoor.net/menus | AD46: HTML | AI46: 2026-06 | AJ46: 2026-06-19 | AK46: Enriched
A47: 45 | B47: Il Bistro | C47: Pike Place | D47: https://www.ilbistro.net | E47: Italian | F47: $$$ | G47: candlelit;romantic | H47: Il Bistro has hidden beneath Pike Place on a cobblestone lane since 1975 - candlelit, low-ceilinged, and unapologetically romantic, pouring Barolo alongside house-made gnocchi and a famous rack of lamb. The date you book when you want dim light and an old-school Italian hush, with the bar pouring until 2am for the lingering type. | I47: Restaurant | J47: 93 Pike St Ste A, Seattle, WA 98101 | K47: (206) 682-3049 | L47: Italian | M47: Daily 5pm-2am (kitchen earlier) | N47: Yes | O47: OpenTable | P47: Y | Q47: N | R47: N | S47: Candlelit; Romantic; Classic | T47: Quiet | U47: 5 | V47: N | X47: 820+ | Y47: Candlelit cobblestone-lane Italian since 1975; famed lamb | Z47: Rack of lamb | AA47: House-made gnocchi | AB47: $30-50 | AC47: https://www.ilbistro.net/ | AD47: HTML | AI47: 2026-06 | AJ47: 2026-06-19 | AK47: Enriched
A48: 46 | B48: Cutters Crabhouse | C48: Pike Place | D48: https://www.cutterscrabhouse.com | E48: Seafood | F48: $$$ | G48: waterfront;view | H48: Cutters Crabhouse trades on one of the best dinner views in the city - floor-to-ceiling windows over Elliott Bay and the ferries - paired with Dungeness crab, Northwest seafood, and even sushi. It leans a touch touristy, but for a sunset date with the water glowing pink, the room earns it. Ask for a window table. | I48: Restaurant | J48: 2001 Western Ave, Seattle, WA 98121 | K48: (206) 448-4884 | L48: Seafood/waterfront | M48: Daily 11:30am-9pm (Fri-Sat to 9:30) | N48: Yes | O48: OpenTable | P48: Y | Q48: Y | R48: Y | S48: Waterfront; View; Lively | T48: Moderate | U48: 3 | V48: N | X48: 1960+ | Y48: Panoramic Elliott Bay views; Dungeness crab, NW seafood | Z48: Dungeness crab | AA48: Crab & artichoke dip | AB48: $30-55 | AC48: https://www.cutterscrabhouse.com/menus/ | AD48: HTML | AI48: 2026-06 | AJ48: 2026-06-19 | AK48: Enriched
A49: 47 | B49: Radiator Whiskey | C49: Pike Place | D49: https://www.radiatorwhiskey.com | E49: American | F49: $$$ | G49: bar;fun | H49: Radiator Whiskey is a rowdy, meat-forward 21-plus den on the top floor of the Corner Market - bourbon flights, a whole smoked pig's head for the table, brisket and cornbread. Loud, fun, and a little carnivorous, a date for two who'd rather split a pile of smoked meat and a whiskey list than whisper over candlelight. | I49: Restaurant | J49: 94 Pike St Ste 30, Seattle, WA 98101 | K49: (206) 467-4268 | L49: Whiskey bar/smoked meats | M49: Mon-Thu 3-10pm; Fri-Sat 3-11pm; Sun closed | N49: Yes | O49: OpenTable | P49: N | Q49: N | R49: Y | S49: Rowdy; Fun; Carnivorous | T49: Loud | U49: 3 | V49: N | X49: 1490+ | Y49: 21+ whiskey + smoked meats; pig's head for two | Z49: Smoked pig head (for 2) | AA49: Beef brisket | AB49: $20-40 | AC49: https://www.radiatorwhiskey.com/pikeplacemarket/ | AD49: HTML | AI49: 2026-06 | AJ49: 2026-06-19 | AK49: Enriched
A50: 48 | B50: How to Cook a Wolf | C50: Queen Anne | D50: https://howtocookawolf.com/ | E50: Italian | F50: $$$ | G50: intimate;romantic | H50: How to Cook a Wolf is Ethan Stowell's moody Queen Anne flagship - a tight menu of handmade pasta and Italian-inflected small plates on Northwest ingredients, poured alongside bold wines in a dim, intimate room. A long-running date-night favorite for good reason: refined, unhurried, and made for sharing four or five plates. | I50: Restaurant | J50: 2208 Queen Anne Ave N, Seattle, WA 98109 | K50: (206) 838-8090 | L50: Italian small plates | M50: Daily 4-10pm | N50: Yes | O50: OpenTable | P50: Y | Q50: N | R50: Y | S50: Moody; Intimate; Refined | T50: Moderate | U50: 4 | V50: N | X50: 1200+ | Y50: Ethan Stowell's intimate Italian small-plates room | Z50: Handmade pasta | AA50: Seasonal small plates | AB50: $20-35 | AC50: https://howtocookawolf.com/ | AD50: HTML | AI50: 2026-06 | AJ50: 2026-06-19 | AK50: Enriched
A51: 49 | B51: Eden Hill | C51: Queen Anne | D51: https://www.edenhillrestaurant.com | E51: Pacific NW | G51: tasting-menu;special | I51: Restaurant | Y51: Closed (2026) | AJ51: 2026-06-19 | AK51: CLOSED - drop
A52: 50 | B52: Toulouse Petit | C52: Queen Anne | D52: https://www.toulousepetit.com | E52: Cajun | F52: $$$ | G52: lively;brunch-date | H52: Toulouse Petit brings the French Quarter to Lower Queen Anne - a dim, ornate room of New Orleans cooking, gumbo and beignets and one of the city's best happy hours, open late. Lively rather than hushed, a fun, slightly raucous date before a show at the Seattle Center across the street. | I52: Restaurant | J52: 601 Queen Anne Ave N, Seattle, WA 98109 | K52: (206) 432-9069 | L52: Cajun/Creole | M52: Daily 3:30-11pm (Fri-Sat to 12am) | N52: Yes | O52: OpenTable | P52: Y | Q52: N | R52: Y | S52: Lively; Ornate; Festive | T52: Loud | U52: 3 | V52: N | X52: 5400+ | Y52: New Orleans cooking, big happy hour, beignets, open late | Z52: Shrimp & grits | AA52: Beignets | AB52: $20-38 | AC52: https://www.toulousepetit.com/our-menus/ | AD52: HTML | AI52: 2026-06 | AJ52: 2026-06-19 | AK52: Enriched
A53: 51 | B53: Taylor Shellfish Oyster Bar | C53: Queen Anne | D53: https://www.taylorshellfishfarms.com | E53: Seafood | F53: $$$ | G53: oysters;casual-date | H53: Taylor Shellfish's Queen Anne oyster bar is tide-to-table at its most direct - oysters, clams, and geoduck from the family's own farms, shucked while you watch, steps from the Space Needle. Casual and counter-driven, first-come only, a breezy, briny date over a dozen on the half shell and a crisp white. | I53: Restaurant | J53: 124 Republican St, Seattle, WA 98109 | K53: (206) 501-4442 | L53: Oyster bar/Shellfish | M53: Mon-Thu 12-8pm; Fri-Sat 12-9pm; Sun 12-8pm | N53: Walk-in | O53: First-come | P53: Y | Q53: N | R53: Y | S53: Casual; Fresh; Patio | T53: Moderate | U53: 3 | V53: Y | X53: 860+ | Y53: Tide-to-table oyster bar from the 1890s shellfish family | Z53: Oysters on the half shell | AA53: Geoduck | AB53: $20-40 | AC53: https://www.taylorshellfishfarms.com/locations/queen-anne | AD53: HTML | AI53: 2026-06 | AJ53: 2026-06-19 | AK53: Enriched
A54: 52 | B54: Via Tribunali | C54: Queen Anne | D54: https://www.viatribunali.com | E54: Italian | F54: $$ | G54: pizza;cozy | H54: Via Tribunali fires certified Neapolitan pizza in a dark, candle-and-brick room atop Queen Anne - blistered margherita, clam-and-mussel frutti di mare, a short list of antipasti. Cozy and low-key, the easy weeknight date where you split a couple of pies and a Chianti without fuss or a big bill. | I54: Restaurant | J54: 317 W Galer St, Seattle, WA 98119 | K54: (206) 264-7768 | L54: Neapolitan pizza | M54: Tue-Sun 4-9pm (Fri-Sat to 10) | N54: Yes | O54: OpenTable | P54: Y | Q54: N | R54: N | S54: Cozy; Candlelit; Casual | T54: Moderate | U54: 3 | V54: N | X54: 290+ | Y54: Certified Neapolitan pizza in a dark, cozy room | Z54: Margherita pizza | AA54: Frutti di mare pizza | AB54: $16-26 | AC54: https://www.viatribunali.com/menus/ | AD54: HTML | AI54: 2026-06 | AJ54: 2026-06-19 | AK54: Enriched
A55: 53 | B55: Grappa | C55: Queen Anne | D55: https://www.grappaseattle.com | E55: Mediterranean | F55: $$$ | G55: romantic;wine | H55: Grappa is a casual-elegant Mediterranean room at the top of Queen Anne - shareable mezze and small plates, handmade pasta, and a deep grappa and wine list. A reliable pre-theater date before McCaw Hall, warm and unfussy, the kind of neighborhood spot that's easy to book and hard to fault. | I55: Restaurant | J55: 2 W Boston St, Seattle, WA 98119 | K55: (206) 829-8995 | L55: Mediterranean/Italian | M55: Daily to 9-10pm | N55: Yes | O55: OpenTable | P55: Y | Q55: Y | R55: Y | S55: Casual-elegant; Romantic; Warm | T55: Moderate | U55: 4 | V55: Y | X55: 530+ | Y55: Casual-elegant Mediterranean; mezze, pasta, grappa list | Z55: Mezze small plates | AA55: Handmade pasta | AB55: $22-38 | AC55: https://grappaseattle.com/menu/ | AD55: HTML | AI55: 2026-06 | AJ55: 2026-06-19 | AK55: Enriched
A56: 54 | B56: Peso’s | C56: Queen Anne | D56: https://www.pesoskitchen.com | E56: Latin | G56: late-night;bar | I56: Restaurant | Y56: Closed (Feb 2026) | AJ56: 2026-06-19 | AK56: CLOSED - drop
A57: 55 | B57: Citizen | C57: Queen Anne | D57: https://www.citizencoffee.com | E57: American | F57: $$ | G57: patio;casual-date | H57: Citizen is a Lower Queen Anne cafe that stretches into the evening - crepes, Vietnamese-style sandwiches, salads, and a short cocktail list, with a sunny patio near the Seattle Center. A low-key, casual date, better for a relaxed early bite than a big night, but easy and friendly with something for most appetites. | I57: Cafe | J57: 706 Taylor Ave N, Seattle, WA 98109 | K57: (206) 284-1015 | L57: Cafe/Crepes | M57: Tue-Thu 3-9pm; Fri-Sun to 9-10pm | N57: Yes | O57: OpenTable | P57: Y | Q57: Y | R57: Y | S57: Casual; Patio; Relaxed | T57: Moderate | U57: 2 | V57: Y | X57: 1180+ | Y57: Cafe-into-evening; crepes, banh mi, patio, cocktails | Z57: Savory crepes | AA57: Vietnamese-style sandwich | AB57: $14-22 | AC57: https://www.citizencoffee.com | AD57: HTML | AI57: 2026-06 | AJ57: 2026-06-19 | AK57: Enriched
A58: 56 | B58: Streamline Tavern | C58: Queen Anne | D58: https://www.streamlinetavern.com | E58: Bar | F58: $ | G58: divey;fun | H58: Streamline Tavern is the quintessential Queen Anne dive - light-up sign, free peanuts, pool and darts in back, and unfussy comfort food like the Porkenstein dog and taco baskets. Not a fancy date, a fun one: cheap beer, Taco Thursdays, and zero pretense for two who'd rather play pool than read a wine list. | I58: Bar | J58: 174 Roy St, Seattle, WA 98109 | K58: (206) 501-0024 | L58: Pub/comfort food | M58: Daily 12pm-2am | N58: Walk-in | O58: Walk-in | P58: Y | Q58: N | R58: N | S58: Divey; Fun; Casual | T58: Loud | U58: 2 | V58: N | X58: 117+ | Y58: Queen Anne dive bar; comfort food, pool, Taco Thursdays | Z58: Porkenstein dog | AA58: Taco basket | AB58: $8-15 | AC58: https://www.streamlinetavern.com | AD58: HTML | AI58: 2026-06 | AJ58: 2026-06-19 | AK58: Enriched
A59: 57 | B59: Barrio Queen Anne | C59: Queen Anne | D59: https://www.barriorestaurant.com | E59: Mexican | G59: lively;cocktails | I59: Restaurant | Y59: Permanently closed Aug 2024 - now Mint & Martini | AJ59: 2026-06-19 | AK59: CLOSED - drop
A60: 58 | B60: Tilth | C60: Wallingford | D60: https://www.tilthrestaurant.com | E60: Pacific NW | G60: romantic;organic | I60: Restaurant | Y60: Closed (May 2026) | AJ60: 2026-06-19 | AK60: CLOSED - drop
A61: 59 | B61: Cantinetta | C61: Wallingford | D61: https://www.cantinettaseattle.com | E61: Italian | F61: $$$ | G61: candlelit;romantic | H61: Cantinetta is a warm, candlelit Tuscan room in the heart of Wallingford - daily handmade pasta (the tagliatelle and ricotta agnolotti have a following), burrata, chanterelle risotto, and a tidy Italian wine list. Quietly romantic and consistently excellent, a neighborhood date that punches above its unassuming storefront. | I61: Restaurant | J61: 3650 Wallingford Ave N, Seattle, WA 98103 | K61: (206) 632-1000 | L61: Tuscan | M61: Tue-Sun 5-9:30pm (Fri-Sat to 10) | N61: Yes | O61: OpenTable | P61: Y | Q61: N | R61: Y | S61: Candlelit; Romantic; Warm | T61: Moderate | U61: 4 | V61: N | X61: 500+ | Y61: Candlelit Tuscan; daily handmade pasta, Italian wine | Z61: Tagliatelle | AA61: Ricotta agnolotti | AB61: $24-38 | AC61: https://www.cantinettausa.com/wallingford1 | AD61: HTML | AI61: 2026-06 | AJ61: 2026-06-19 | AK61: Enriched
A62: 60 | B62: Joule | C62: Wallingford | D62: https://www.joulerestaurant.com | E62: Korean-Fusion | F62: $$$ | G62: creative;date-night | H62: Joule is Rachel Yang's modern Korean steakhouse - short rib in chili-anchovy butter, spicy rice cakes, beef tartare, and a famous brunch, all bold and bass-forward. The room is lively and design-y, a creative, energetic date for two who want their Korean fusion adventurous and their cocktails sharp. | I62: Restaurant | J62: 3506 Stone Way N, Seattle, WA 98103 | K62: (206) 632-5685 | L62: Korean steakhouse/fusion | M62: Dinner nightly (reserve 1.75-3hr slots) | N62: Yes | O62: OpenTable | P62: Y | Q62: N | R62: Y | S62: Creative; Lively; Design-y | T62: Loud | U62: 4 | V62: Y | X62: 1170+ | Y62: Modern Korean steakhouse; short rib, spicy rice cakes | Z62: Short rib steak | AA62: Spicy rice cakes | AB62: $20-40 | AC62: https://www.joulerestaurant.com | AD62: HTML | AI62: 2026-06 | AJ62: 2026-06-19 | AK62: Enriched
A63: 61 | B63: Korean Tofu House | C63: Wallingford | D63: https://www.koreantofuhouse.com | E63: Korean | G63: casual-date | I63: Restaurant | Y63: Same business as U District location (4142 Brooklyn Ave NE) - dedupe; not in Wallingford | AJ63: 2026-06-19 | AK63: Review
A64: 62 | B64: Pam's Caribbean Kitchen | C64: Wallingford | D64: https://www.pams-kitchen.com | E64: Caribbean | F64: $$ | G64: warm;cozy | H64: Pam's Caribbean Kitchen is a warm, family-run Wallingford spot for Trinidadian home cooking - jerk chicken, curry goat, roti, and slow-simmered curries made fresh daily, with strong vegan and gluten-free options. Casual and generous rather than romantic, a cozy, flavorful date that won't break the bank. Wednesday is all-you-can-eat. | I64: Restaurant | J64: 1715 N 45th St, Seattle, WA 98103 | K64: (206) 696-7010 | L64: Trinidadian/Caribbean | M64: Wed-Sun (Thu-Sun 4-10/11pm; Fri from 12) | N64: Walk-in | O64: Walk-in | P64: Y | Q64: Y | R64: Y | S64: Warm; Cozy; Casual | T64: Moderate | U64: 3 | V64: N | X64: 590+ | Y64: Family-run Trinidadian; jerk chicken, curry goat, roti | Z64: Curry goat | AA64: Jerk chicken | AB64: $15-25 | AC64: https://pams-kitchen.com/ | AD64: HTML | AI64: 2026-06 | AJ64: 2026-06-19 | AK64: Enriched
A65: 63 | B65: Musashi's | C65: Wallingford | D65: https://musashis-3.wheree.com/ | E65: Japanese/Sushi | F65: $ | G65: intimate;chef-driven | H65: Musashi's is the cult cheap-sushi counter of Wallingford - fresh, generous rolls and nigiri at prices that have drawn lines for decades. Tiny, no-frills, and cash-friendly, not a special-occasion room but a beloved everyday one. A low-key, budget-happy date when you just want good fish without ceremony. | I65: Restaurant | J65: 1400 N 45th St, Seattle, WA 98103 | K65: (206) 633-0212 | L65: Casual sushi | M65: Daily 11am-9pm | N65: Walk-in | O65: Walk-in (cash-friendly) | P65: Y | Q65: N | R65: N | S65: Casual; No-frills; Cheap | T65: Moderate | U65: 2 | V65: N | X65: 1370+ | Y65: Cult cheap-sushi counter; generous rolls, lines out the door | Z65: Sushi rolls | AA65: Nigiri sets | AB65: $12-22 | AC65: https://musashis-3.wheree.com/ | AD65: HTML | AI65: 2026-06 | AJ65: 2026-06-19 | AK65: Enriched
A66: 64 | B66: Bizzarro Italian Café | C66: Wallingford | D66: https://www.bizarroitaliancafe.com | E66: Italian | F66: $$ | G66: quirky;romantic | H66: Bizzarro is Wallingford's beloved oddball - nearly 40 years of eclectic, art-cluttered rooms (furniture hangs from the ceiling) and seriously good house-made pasta. Quirky and candlelit at once, a fun, unpretentious date with real cooking behind the kitsch. Sundays are spaghetti-and-meatballs by tradition. | I66: Restaurant | J66: 1307 N 46th St, Seattle, WA 98103 | K66: (206) 632-7277 | L66: Eclectic Italian | M66: Daily 3-9pm | N66: Yes | O66: OpenTable | P66: Y | Q66: N | R66: Y | S66: Quirky; Romantic; Fun | T66: Moderate | U66: 4 | V66: N | X66: 1060+ | Y66: Eclectic 40-year Italian; house pasta, kitschy charm | Z66: House-made pasta | AA66: Spaghetti & meatballs (Sun) | AB66: $18-30 | AC66: https://www.bizzarroitaliancafe.com/wallingford | AD66: HTML | AI66: 2026-06 | AJ66: 2026-06-19 | AK66: Enriched
A67: 65 | B67: Kisaku | C67: Wallingford | D67: https://www.kisaku.com | E67: Japanese/Sushi | F67: $$$ | G67: classic;quiet | H67: Kisaku is Tangletown's quietly excellent sushi house - pristine nigiri, a short list of clever rolls like the Green Lake, and white-tablecloth calm by night. An under-the-radar date spot, refined but unpretentious, the kind of neighborhood sushi bar regulars guard. Sit at the bar and let the chef steer. | I67: Restaurant | J67: 2101 N 55th St Ste 100, Seattle, WA 98103 | K67: (206) 545-9050 | L67: Sushi/Nigiri | M67: Mon-Thu/Sun 5-8:45pm; Fri-Sat 5-9:15pm | N67: Yes | O67: OpenTable | P67: Y | Q67: N | R67: Y | S67: Quiet; Refined; Under-the-radar | T67: Quiet | U67: 4 | V67: N | X67: 840+ | Y67: Tangletown sushi; pristine nigiri, white-tablecloth nights | Z67: Nigiri assortment | AA67: Green Lake Roll | AB67: $25-45 | AC67: https://www.kisaku.com/ | AD67: HTML | AI67: 2026-06 | AJ67: 2026-06-19 | AK67: Enriched
A68: 66 | B68: Union Saloon | C68: Wallingford | D68: https://www.unionsaloon.com | E68: American | F68: $$ | G68: neighborhood;cozy | H68: Union Saloon is a snug Wallingford corner of craft beer, affordable wine, and re-envisioned comfort food that changes constantly. The horseshoe bar and easy menu make it more neighborhood-hangout than grand night out, but it's a relaxed, friendly date with cooking that takes itself just seriously enough. | I68: Restaurant | J68: 3645 Wallingford Ave N, Seattle, WA 98103 | K68: (206) 547-2280 | L68: American comfort/cocktail bar | M68: Tue-Thu 4:30-9pm; Fri-Sat to 10pm | N68: Walk-in | O68: Walk-in | P68: Y | Q68: N | R68: N | S68: Cozy; Neighborhood; Relaxed | T68: Moderate | U68: 3 | V68: N | X68: 180+ | Y68: Craft beer + re-envisioned comfort food, horseshoe bar | Z68: Rotating comfort plates | AA68: Burger | AB68: $16-26 | AC68: https://www.unionsaloonseattle.com/dinner | AD68: HTML | AI68: 2026-06 | AJ68: 2026-06-19 | AK68: Enriched
A69: 67 | B69: Red Cow | C69: Madrona | D69: https://ethanstowellrestaurants.com/restaurants/red-cow-madrona-seattle | E69: Steakhouse | F69: $$$ | G69: romantic;classic | H69: Red Cow is Ethan Stowell's snug French steakhouse in Madrona - steak frites, house-butchered cuts, escargot, and bold reds in a dim, brick-walled bistro. Romantic in the old Parisian way, intimate and unfussy, the neighborhood date you book when you want red wine, red meat, and low candlelight. | I69: Restaurant | J69: 1423 34th Ave, Seattle, WA 98122 | K69: (206) 454-7932 | L69: French steakhouse/bistro | M69: Daily 3-9pm | N69: Yes | O69: OpenTable | P69: Y | Q69: N | R69: Y | S69: Romantic; Classic; Intimate | T69: Moderate | U69: 4 | V69: N | X69: 390+ | Y69: Ethan Stowell French steakhouse; steak frites, bold reds | Z69: Steak frites | AA69: Escargot | AB69: $28-45 | AC69: https://ethanstowellrestaurants.com/restaurants/red-cow-madrona-seattle | AD69: HTML | AI69: 2026-06 | AJ69: 2026-06-19 | AK69: Enriched
A70: 68 | B70: Vendemmia | C70: Madrona | D70: https://www.vendemmia.com | E70: Italian | F70: $$$ | G70: intimate;romantic | H70: Vendemmia is Brian Clevenger's intimate Madrona Italian - silky handmade pastas (the squash agnolotti is the signature), beef tartare, seared scallops, and a thoughtful wine list in a small, serene room. Quietly romantic and reliably refined, a date built for lingering over four courses. The patio happy hour is a local secret. | I70: Restaurant | J70: 1126 34th Ave, Seattle, WA 98122 | K70: (206) 466-2533 | L70: Italian/New American | M70: Daily 5-10pm | N70: Yes | O70: OpenTable | P70: Y | Q70: N | R70: Y | S70: Intimate; Romantic; Refined | T70: Moderate | U70: 4 | V70: Y | X70: 267+ | Y70: Brian Clevenger Italian; squash agnolotti, scallops | Z70: Squash agnolotti | AA70: Beef tartare | AB70: $26-42 | AC70: https://www.vendemmiaseattle.com/ | AD70: HTML | AI70: 2026-06 | AJ70: 2026-06-19 | AK70: Enriched
A71: 69 | B71: Bottlehouse | C71: Madrona | D71: https://www.bottlehouseseattle.com | E71: Bar/Wine | F71: $$ | G71: garden;romantic | H71: Bottlehouse is a wine bar in a 1905 Craftsman with a string-lit garden that's pure Madrona romance - natural wines by the flight, a serious cheese-and-charcuterie program, and small plates for grazing. Relaxed and intimate, the date for two who'd rather discover an obscure bottle and share a board than commit to a tasting menu. | I71: Bar | J71: 1416 34th Ave, Seattle, WA 98122 | K71: (206) 708-7164 | L71: Wine bar/small plates | M71: Tue-Sun 3-9pm (Thu-Sat to 10) | N71: Yes | O71: Resy | P71: Y | Q71: Y | R71: Y | S71: Garden; Romantic; Cozy | T71: Moderate | U71: 4 | V71: Y | X71: 420+ | Y71: Natural-wine bar in a Craftsman; cheese, charcuterie, garden | Z71: Cheese & charcuterie board | AA71: Seasonal small plates | AB71: $15-30 | AC71: https://bottlehouseseattle.com/ | AD71: HTML | AI71: 2026-06 | AJ71: 2026-06-19 | AK71: Enriched
A72: 70 | B72: Hi Spot Café | C72: Madrona | D72: https://www.hispotcafe.com | E72: American | G72: brunch-date | I72: Restaurant | Y72: Breakfast/lunch only (closes 3pm), no dinner - exclude per dinner-only rule | AJ72: 2026-06-19 | AK72: Review
A73: 71 | B73: Madrona Arms | C73: Madrona | D73: https://www.madronaarms.com | E73: Gastropub | F73: $$ | G73: casual;neighborhood | H73: Madrona Arms is a proper British-Irish corner pub - Guinness on tap, fish and chips, bangers and mash, shepherd's pie, and a Madrona burger locals swear by. Warm, woody, and unpretentious, a low-key date for two who want a pint and comfort food rather than a scene. Walk in and settle into a booth. | I73: Restaurant | J73: 1138 34th Ave, Seattle, WA 98122 | K73: (206) 739-5104 | L73: British/Irish gastropub | M73: Mon-Thu 11:30am-11pm; Fri-Sat to 12am; Sun to 10 | N73: Walk-in | O73: Walk-in | P73: Y | Q73: N | R73: N | S73: Cozy; Neighborhood; Pub | T73: Moderate | U73: 3 | V73: N | X73: 130+ | Y73: British-Irish pub; Guinness, fish & chips, shepherd's pie | Z73: Fish and chips | AA73: Bangers and mash | AB73: $16-26 | AC73: http://www.madronaarms.com/menu | AD73: HTML | AI73: 2026-06 | AJ73: 2026-06-19 | AK73: Enriched
A74: 72 | B74: Nirmal's | C74: Madrona-adjacent | D74: https://www.nirmalseattle.com | E74: Indian | F74: $$$ | G74: romantic;refined | H74: Nirmal's brings polished, regional Indian to a handsome Pioneer Square room - goat curry, dal makhani, kofta, and one of the city's best vegetarian and vegan rosters, plated with real care. Refined without being stuffy, a romantic date that proves Indian cooking belongs in the special-occasion conversation. | I74: Restaurant | J74: 106 Occidental Ave S, Seattle, WA 98104 | K74: (206) 683-9701 | L74: Regional Indian | M74: Daily 5:30-10pm | N74: Yes | O74: OpenTable | P74: Y | Q74: Y | R74: Y | S74: Refined; Romantic; Upscale | T74: Moderate | U74: 4 | V74: N | X74: 1050+ | Y74: Upscale regional Indian in Pioneer Square; strong veg/vegan | Z74: Goat curry | AA74: Dal makhani | AB74: $22-36 | AC74: https://www.nirmalseattle.com/ | AD74: HTML | AI74: 2026-06 | AJ74: 2026-06-19 | AK74: Enriched
A75: 73 | B75: Cafe Soleil | C75: Madrona | D75: https://www.cafesoleil.com | E75: Ethiopian | F75: $$ | G75: cozy;casual-date | H75: Cafe Soleil has served Madrona for three decades with a split personality - American brunch by day, authentic Ethiopian by night. Dinner means communal platters of doro wat and vegetarian combos scooped up with injera, the kind of hands-on, shared meal that makes for a warm, conversational date. Cozy, casual, and deeply veg-friendly. | I75: Restaurant | J75: 1400 34th Ave, Seattle, WA 98122 | K75: (206) 325-1126 | L75: Ethiopian | M75: Wed-Fri 5-9pm; Sat 5-8pm | N75: Walk-in | O75: Walk-in | P75: Y | Q75: Y | R75: Y | S75: Cozy; Casual; Communal | T75: Moderate | U75: 3 | V75: N | X75: 110+ | Y75: Ethiopian dinner + American brunch since 1994 | Z75: Doro wat | AA75: Vegetarian combo | AB75: $15-24 | AC75: https://cafesoleil.net/ | AD75: HTML | AI75: 2026-06 | AJ75: 2026-06-19 | AK75: Enriched
A76: 74 | B76: St. Clouds | C76: Madrona | D76: https://www.stclouds.com | E76: American | G76: neighborhood;warm | I76: Restaurant | Y76: Closed (2026) | AJ76: 2026-06-19 | AK76: CLOSED - drop
A77: 75 | B77: The Harvest Vine | C77: Madrona-adjacent | D77: https://www.harvestvine.com | E77: Spanish | F77: $$$ | G77: tapas;romantic | H77: The Harvest Vine is Seattle's enduring Basque tapas room - sit at the copper chef's counter and watch plate after plate of grilled prawns, jamon, and seasonal pintxos emerge, paired with an all-Spanish cellar. Snug, candlelit, and built for two, one of the most quietly romantic counters in the city. Book the kitchen bar. | I77: Restaurant | J77: 2701 E Madison St, Seattle, WA 98112 | K77: (206) 320-9771 | L77: Basque/Spanish tapas | M77: Daily 5-9pm | N77: Yes | O77: Tock | P77: Y | Q77: N | R77: Y | S77: Intimate; Romantic; Chef's counter | T77: Moderate | U77: 5 | V77: N | X77: 766+ | Y77: Enduring Basque tapas; copper chef's counter, Spanish wine | Z77: Grilled prawns | AA77: Seasonal pintxos | AB77: $25-45 | AC77: https://www.harvestvine.com/ | AD77: HTML | AI77: 2026-06 | AJ77: 2026-06-19 | AK77: Enriched
A78: 76 | B78: L'Oursin | C78: Madrona-adjacent | D78: https://www.loursinseattle.com | E78: French | F78: $$$ | G78: wine;romantic | H78: L'Oursin pairs French seafood with a deep natural-wine list in an intimate Central District room - oysters, raw scallops, a rotating peche du jour, and snacks like harissa panisse. A wine-lover's date, low-lit and unhurried, where the bottle is half the conversation. Walk-ins welcome at the bar and patio. | I78: Restaurant | J78: 1315 E Jefferson St, Seattle, WA 98122 | K78: (206) 485-7173 | L78: French seafood/natural wine | M78: Sun-Thu 5-9pm; Fri-Sat 5-9:30pm | N78: Yes | O78: Resy | P78: Y | Q78: N | R78: Y | S78: Intimate; Wine-forward; Romantic | T78: Moderate | U78: 4 | V78: Y | X78: 182+ | Y78: French seafood + natural wine, intimate Central District room | Z78: Oysters | AA78: Peche du jour | AB78: $25-42 | AC78: https://www.loursinseattle.com/ | AD78: HTML | AI78: 2026-06 | AJ78: 2026-06-19 | AK78: Enriched
A79: 77 | B79: The Blue Glass | C79: Phinney Ridge | D79: https://www.theblueglass.com | E79: American | F79: $$$ | G79: cozy;neighborhood | H79: The Blue Glass is a cozy 21-plus garden house on the Phinney-Ballard line - elevated global comfort food, seafood and steak, craft cocktails, and a covered front patio strung for evenings. Intimate and a little hidden, the kind of relaxed neighborhood date where the cocktails are serious and the room never gets too loud. | I79: Restaurant | J79: 704 NW 65th St, Seattle, WA 98117 | K79: (206) 420-1631 | L79: New American/seafood-steak | M79: Daily 4-9pm | N79: Yes | O79: OpenTable | P79: Y | Q79: Y | R79: Y | S79: Cozy; Garden patio; Intimate | T79: Moderate | U79: 4 | V79: Y | X79: 356+ | Y79: 21+ garden house; global comfort, seafood, steak, cocktails | Z79: Seafood plates | AA79: Steak | AB79: $22-38 | AC79: https://www.theblueglass.org/menus | AD79: HTML | AI79: 2026-06 | AJ79: 2026-06-19 | AK79: Enriched
A80: 78 | B80: Cornuto | C80: Phinney Ridge | D80: https://www.cornutopizzeria.com | E80: Italian | F80: $$ | G80: pizza;romantic | H80: Cornuto is Via Tribunali's Phinney Ridge pizzeria - proper wood-fired Neapolitan pies (the Bufalina DOC is the order), a tight cocktail list, and tiramisu worth saving room for. Small and candle-warm, an easy, affordable date where you split a couple of blistered pizzas and a bottle of Italian red. | I80: Restaurant | J80: 7404 Greenwood Ave N, Seattle, WA 98103 | K80: (206) 812-0416 | L80: Neapolitan pizza | M80: Wed-Sun 4-9:30pm | N80: Yes | O80: OpenTable | P80: Y | Q80: N | R80: N | S80: Cozy; Candlelit; Casual | T80: Moderate | U80: 3 | V80: N | X80: 271+ | Y80: Via Tribunali's Phinney pizzeria; wood-fired Neapolitan | Z80: Bufalina DOC pizza | AA80: Tiramisu | AB80: $16-26 | AC80: https://www.cornutopizzeria.com/ | AD80: HTML | AI80: 2026-06 | AJ80: 2026-06-19 | AK80: Enriched
A81: 79 | B81: Windy City Pie | C81: Phinney Ridge | D81: https://www.windycitypie.com | E81: Pizza | F81: $$ | G81: casual-date | H81: Windy City Pie makes the deep dish Seattle argues about - a caramelized-crust Chicago pie heavy enough to anchor a table, plus tavern-thin slices and a little digestif bar. You preorder your bake time, which makes it a planned-out casual date: show up, claim a booth, and split a pie that could feed three. | I81: Restaurant | J81: 5918 Phinney Ave N, Seattle, WA 98103 | K81: (206) 486-4743 | L81: Chicago deep-dish pizza | M81: Tue-Thu 4-9pm; Fri-Sun 12-10pm | N81: No | O81: Preorder online | P81: Y | Q81: N | R81: N | S81: Casual; Cult; Laid-back | T81: Moderate | U81: 3 | V81: N | X81: 670+ | Y81: Cult Chicago deep dish; preorder bake time, digestif bar | Z81: Deep-dish pizza | AA81: Tavern thin-crust | AB81: $20-35 | AC81: https://windycitypie.com/menu/ | AD81: HTML | AI81: 2026-06 | AJ81: 2026-06-19 | AK81: Enriched
A82: 80 | B82: Olive and Grape | C82: Phinney Ridge | D82: https://www.theoliveandgrape.com | E82: Mediterranean | G82: warm;romantic | I82: Restaurant | Y82: Closed (2026) after 15 years | AJ82: 2026-06-19 | AK82: CLOSED - drop
A83: 81 | B83: Hecho | C83: Greenwood | D83: https://www.hechoseattle.com | E83: Mexican | G83: lively;fun | I83: Restaurant | Y83: Closed (Feb 2026) | AJ83: 2026-06-19 | AK83: CLOSED - drop
A84: 82 | B84: Opus Co. | C84: Phinney Ridge | D84: https://www.opuscorestaurant.com | E84: Pacific NW | G84: tasting-menu;intimate | I84: Restaurant | Y84: Yelp shows CLOSED (Jun 2026); reservation site still active - verify | AJ84: 2026-06-19 | AK84: Review
A85: 83 | B85: The Yard Café | C85: Greenwood | D85: https://www.theyardcafe.com | E85: Latin | F85: $$ | G85: casual;patio | H85: The Yard Cafe does Latin-inflected comfort food with a wall of rotating drafts and scratch margaritas - duck-leg confit, shrimp tacos, a solid burger - in a laid-back Greenwood room with a patio. A fun, unfussy date built around good cocktails and shareable plates rather than ceremony. | I85: Restaurant | J85: 8313 Greenwood Ave N, Seattle, WA 98103 | K85: (206) 588-1746 | L85: Latin comfort food | M85: Daily 11am-9pm (Tue-Sat to 10) | N85: Yes | O85: OpenTable | P85: Y | Q85: N | R85: Y | S85: Casual; Fun; Patio | T85: Moderate | U85: 3 | V85: Y | X85: 356+ | Y85: Latin comfort food, rotating drafts, scratch margaritas | Z85: Duck leg confit | AA85: Shrimp tacos | AB85: $15-26 | AC85: https://theyardcafe.com/ | AD85: HTML | AI85: 2026-06 | AJ85: 2026-06-19 | AK85: Enriched
A86: 84 | B86: Naked City Brewery | C86: Greenwood | D86: https://www.nakedcitybrewing.com | E86: Gastropub | G86: casual;events | I86: Brewery | Y86: Closed (2026) after 10 years | AJ86: 2026-06-19 | AK86: CLOSED - drop
A87: 85 | B87: Bongos | C87: Greenwood | D87: https://www.bongosseattle.com | E87: Caribbean | F87: $ | G87: beachy;fun | H87: Bongos is a Caribbean playground in a repurposed Aurora gas station near Green Lake - Cuban sandwiches, jerk plates, plantains, and frozen drinks on a sunny patio. Cheap, breezy, and cash-easy, less a date-night destination than a fun, sunshine-y casual bite when you want island flavors without a fuss. | I87: Restaurant | J87: 6501 Aurora Ave N, Seattle, WA 98103 | K87: (206) 420-8548 | L87: Cuban/Caribbean | M87: Tue-Sun 11am-9pm | N87: Walk-in | O87: Walk-in | P87: Y | Q87: Y | R87: N | S87: Casual; Breezy; Patio | T87: Moderate | U87: 2 | V87: Y | X87: 1530+ | Y87: Caribbean cafe in a repurposed gas station; Cuban sandwiches | Z87: Cuban sandwich | AA87: Jerk plate | AB87: $12-20 | AC87: http://www.bongosseattle.com/ | AD87: HTML | AI87: 2026-06 | AJ87: 2026-06-19 | AK87: Enriched
A88: 86 | B88: Saltoro | C88: Greenwood | D88: https://www.saltororestaurant.com | E88: American | F88: $$$ | G88: romantic;neighborhood | H88: Saltoro is North Greenwood's polished all-rounder - handmade pasta, steak frites, a cult lamb burger, and truffle fries in a warm, grown-up room that's drawn locals for 15 years. The dependable neighborhood date that does a bit of everything well, easy to book and hard to disappoint. | I88: Restaurant | J88: 14051 Greenwood Ave N, Seattle, WA 98133 | K88: (206) 365-6025 | L88: American/Mediterranean/Italian | M88: Daily 5-9pm (Fri-Sat to 10) | N88: Yes | O88: OpenTable | P88: Y | Q88: N | R88: Y | S88: Warm; Neighborhood; Romantic | T88: Moderate | U88: 4 | V88: N | X88: 365+ | Y88: Polished all-rounder; pasta, steak frites, lamb burger | Z88: Steak frites | AA88: Lamb burger | AB88: $20-38 | AC88: https://www.saltoroseattle.com/ | AD88: HTML | AI88: 2026-06 | AJ88: 2026-06-19 | AK88: Enriched
A89: 87 | B89: Morsel | C89: U District | D89: https://www.morselseattle.com | E89: American | G89: breakfast-date | I89: Restaurant | Y89: Breakfast/lunch only (closes 3pm), no dinner - exclude per dinner-only rule | AJ89: 2026-06-19 | AK89: Review
A90: 88 | B90: Xi’an Noodles | C90: U District | D90: https://www.xiannoodles.com | E90: Chinese | F90: $ | G90: casual-date | H90: Xi'an Noodles slings hand-ripped biang biang noodles in a bare-bones U District room - spicy cumin lamb, tingly beef, chili oil everywhere. Cheap, fast, and gloriously messy, not a romance setting but a fun, low-stakes date for two who bond over numbing spice and a pile of noodles. | I90: Restaurant | J90: 5259 University Way NE, Seattle, WA 98105 | K90: (206) 522-8888 | L90: Shaanxi Chinese | M90: Daily 11am-9pm | N90: Walk-in | O90: Walk-in | P90: Y | Q90: N | R90: N | S90: Casual; Cheap; Spicy | T90: Moderate | U90: 2 | V90: N | X90: 1190+ | Y90: Hand-ripped biang biang noodles; cumin lamb, chili oil | Z90: Spicy cumin lamb noodles | AA90: Tingly beef noodles | AB90: $11-16 | AC90: https://xiannoodles.com/ | AD90: HTML | AI90: 2026-06 | AJ90: 2026-06-19 | AK90: Enriched
A91: 89 | B91: Agua Verde Café | C91: U District | D91: https://www.aguaverdecafe.com | E91: Mexican | F91: $$ | G91: waterfront;fun | H91: Agua Verde Cafe sits right on Portage Bay - Baja-style tacos and margaritas with a sunny waterfront deck and kayaks for rent below. A U District favorite since 1998, fun and breezy rather than fancy: grab the deck on a warm evening for a casual, sun-soaked date over fish tacos. | I91: Restaurant | J91: 1303 NE Boat St, Seattle, WA 98105 | K91: (206) 545-8570 | L91: Baja Mexican | M91: Daily 11am-9pm | N91: Yes | O91: OpenTable | P91: Y | Q91: Y | R91: Y | S91: Waterfront; Fun; Casual | T91: Moderate | U91: 3 | V91: Y | X91: 1313+ | Y91: Baja tacos on Portage Bay; waterfront deck, kayak rentals | Z91: Fish tacos | AA91: Margaritas | AB91: $14-24 | AC91: https://www.aguaverdecafe.com/ | AD91: HTML | AI91: 2026-06 | AJ91: 2026-06-19 | AK91: Enriched
A92: 90 | B92: Shultzy's | C92: U District | D92: https://www.shultzys.com | E92: German | F92: $$ | G92: casual;beer | H92: Shultzy's has griddled house-made sausages and poured craft beer on the Ave since 1988 - bratwurst, cheesesteaks, burgers, and a long tap list in a rowdy, collegiate bar. A casual, beer-soaked date for two who want a sausage, a stein, and zero pretense near campus. | I92: Bar | J92: 4114 University Way NE, Seattle, WA 98105 | K92: (206) 548-9461 | L92: German sausage/pub | M92: Mon-Thu 11am-12am; Fri-Sat to 1am; Sun closed | N92: Walk-in | O92: Walk-in | P92: Y | Q92: N | R92: N | S92: Casual; Collegiate; Beer bar | T92: Loud | U92: 2 | V92: N | X92: 448+ | Y92: House-made sausages + craft beer on the Ave since 1988 | Z92: Bratwurst | AA92: Cheesesteak | AB92: $12-20 | AC92: https://www.shultzys.com/ | AD92: HTML | AI92: 2026-06 | AJ92: 2026-06-19 | AK92: Enriched
A93: 91 | B93: Korean Tofu House | C93: U District | D93: https://www.koreantofuhouse.com | E93: Korean | F93: $$ | G93: casual-date | H93: Korean Tofu House is the U District's go-to for bubbling soondubu - soft-tofu stews that arrive volcanic at the table, with banchan and a hot stone bowl of rice. Cozy, cheap, and deeply comforting, a casual cold-weather date when you want something warming and unfussy near campus. | I93: Restaurant | J93: 4142 Brooklyn Ave NE, Seattle, WA 98105 | K93: (206) 632-3119 | L93: Korean/Soondubu | M93: Daily 10am-9pm | N93: Walk-in | O93: Walk-in | P93: Y | Q93: N | R93: Y | S93: Cozy; Casual; Comforting | T93: Moderate | U93: 2 | V93: N | X93: 912+ | Y93: U District soondubu specialist; soft-tofu stews, banchan | Z93: Soondubu (soft tofu stew) | AA93: Bibimbap | AB93: $13-20 | AC93: https://koreantofuhouse.com/ | AD93: HTML | AI93: 2026-06 | AJ93: 2026-06-19 | AK93: Enriched
A94: 92 | B94: U:Don | C94: U District | D94: https://www.udonfresh.com | E94: Japanese | F94: $ | G94: casual;quick-date | H94: U:Don makes fresh, hand-cut udon to order in a cafeteria-style U District shop - chewy noodles in dashi, crisp tempura you grab on the way to the register. Fast, cheap, and satisfying, an everyday casual bite rather than a date destination, but a cozy, slurpable stop on a budget. | I94: Restaurant | J94: 4515 University Way NE, Seattle, WA 98105 | K94: (206) 547-7811 | L94: Japanese udon | M94: Daily 11am-8:30pm (Fri-Sat to 9) | N94: Walk-in | O94: Counter/cafeteria | P94: Y | Q94: Y | R94: N | S94: Casual; Quick; Cheap | T94: Moderate | U94: 2 | V94: N | X94: 840+ | Y94: Fresh hand-cut udon, cafeteria-style; tempura | Z94: Udon in dashi | AA94: Tempura | AB94: $9-15 | AC94: https://www.freshudon.com/menu | AD94: HTML | AI94: 2026-06 | AJ94: 2026-06-19 | AK94: Enriched
A95: 93 | B95: Taste of Xi'an | C95: U District | D95: https://www.tasteofxian.com | E95: Chinese | F95: $ | G95: casual;spicy | H95: Taste of Xi'an brings Shaanxi street food to the Ave - hand-pulled noodles, cumin lamb burgers, and bold, rustic Northern Chinese plates. Casual and inexpensive like its neighbors, a fun, spicy, fill-up-for-cheap date for two who'd rather chase flavor than ambience. | I95: Restaurant | J95: 4523 University Way NE, Seattle, WA 98105 | K95: (206) 231-9999 | L95: Shaanxi Chinese | M95: Daily 11am-9:30pm (Mon-Fri break 3:30-5) | N95: Walk-in | O95: Walk-in | P95: Y | Q95: N | R95: N | S95: Casual; Cheap; Spicy | T95: Moderate | U95: 2 | V95: N | X95: 568+ | Y95: Shaanxi street food; hand-pulled noodles, cumin lamb burger | Z95: Hand-pulled noodles | AA95: Cumin lamb burger | AB95: $10-16 | AC95: https://everout.com/seattle/locations/taste-of-xian/l14776/ | AD95: HTML | AI95: 2026-06 | AJ95: 2026-06-19 | AK95: Enriched
A96: 94 | B96: Mamma Melina | C96: U District | D96: https://www.mammamelina.com | E96: Italian | F96: $$$ | G96: romantic;classic | H96: Mamma Melina is the U District's warm, white-tablecloth Italian - fresh pasta, wood-fired pizza, and regional wines in a convivial room with a patio. Family-run and a notch dressier than the student spots nearby, an easy, friendly date for handmade pasta and a bottle without trekking downtown. | I96: Restaurant | J96: 5101 25th Ave NE, Seattle, WA 98105 | K96: (206) 632-2271 | L96: Italian/Pizzeria | M96: Daily 3-9pm (Fri-Sat to 10) | N96: Yes | O96: OpenTable | P96: Y | Q96: N | R96: Y | S96: Convivial; Family; Warm | T96: Moderate | U96: 3 | V96: Y | X96: 914+ | Y96: Warm U District Italian; fresh pasta, wood-fired pizza | Z96: Handmade pasta | AA96: Wood-fired pizza | AB96: $20-34 | AC96: https://www.mammamelina.com/menu | AD96: HTML | AI96: 2026-06 | AJ96: 2026-06-19 | AK96: Enriched
A97: 95 | B97: Din Tai Fung | C97: U District | D97: https://www.dintaifungusa.com | E97: Taiwanese | F97: $$ | G97: popular;fun | H97: Din Tai Fung is the soup-dumpling juggernaut at University Village - watch the pleating through the glass, then demolish a steamer of kurobuta xiao long bao with chicken dumplings and garlicky greens. Bustling and walk-in only with a wait, a fun, animated date over endless dumplings rather than a quiet one. | I97: Restaurant | J97: 2621 NE 46th St, Seattle, WA 98105 | K97: (206) 525-0958 | L97: Taiwanese/Dumplings | M97: Daily 11am-9pm (Fri-Sat to 9:30) | N97: Walk-in | O97: Walk-in (waitlist) | P97: Y | Q97: N | R97: N | S97: Bustling; Fun; Popular | T97: Loud | U97: 3 | V97: N | X97: 3000+ | Y97: Soup-dumpling juggernaut; kurobuta xiao long bao | Z97: Kurobuta xiao long bao | AA97: Chicken dumplings | AB97: $15-28 | AC97: https://dtf.com/en-us/locations/seattle-university-village | AD97: HTML | AI97: 2026-06 | AJ97: 2026-06-19 | AK97: Enriched
A98: 96 | B98: Sushi Kappo Tamura | C98: U District | D98: https://www.sushikappotamura.com | E98: Japanese/Sushi | F98: $$$$ | G98: sustainable;romantic | H98: Sushi Kappo Tamura is chef Taichi Kitamura's kappo-style temple to Northwest fish - omakase and seasonal small plates served fast from an open kitchen in a lively room. Serious sushi without the hush, refined but warm, a date for two who want top-tier fish and a bit of kitchen theater. | I98: Restaurant | J98: 2968 Eastlake Ave E, Seattle, WA 98102 | K98: (206) 547-0937 | L98: Kappo/Sushi/Omakase | M98: Tue-Thu 5-9:30pm; Fri-Sat 5-10pm | N98: Yes | O98: OpenTable | P98: N | Q98: N | R98: Y | S98: Refined; Lively; Open-kitchen | T98: Moderate | U98: 4 | V98: N | X98: 613+ | Y98: Kappo-style PNW sushi; omakase, open kitchen | Z98: Omakase | AA98: Seasonal sashimi | AB98: $60-120 | AC98: https://www.sushikappotamura.com/ | AD98: HTML | AI98: 2026-06 | AJ98: 2026-06-19 | AK98: Enriched
A99: 97 | B99: Canlis | C99: Queen Anne | D99: https://canlis.com/ | E99: Pacific NW/American | F99: $$$$ | G99: iconic;special-occasion;view | H99: Canlis is the standard every other Seattle special-occasion dinner is measured against - a 1950 mid-century landmark perched over Lake Union, with a four-course menu, flawless service, and the kind of view proposals are built around. A splurge and a ritual; book weeks out and treat it as the main event. | I99: Restaurant | J99: 2576 Aurora Ave N, Seattle, WA 98109 | K99: (206) 283-3313 | L99: Fine dining/PNW | M99: Tue-Thu 5-10pm; Fri-Sat 5-11pm | N99: Yes | O99: Tock | P99: Y | Q99: N | R99: Y | S99: Iconic; Grand; Romantic; View | T99: Quiet | U99: 5 | V99: N | X99: 1920+ | Y99: Seattle's benchmark fine dining since 1950; Lake Union views | Z99: Four-course tasting | AA99: Canlis salad | AB99: $185 prix fixe | AC99: https://canlis.com/menu | AD99: HTML | AI99: 2026-06 | AJ99: 2026-06-19 | AK99: Enriched
A100: 98 | B100: Sushi Kashiba | C100: Pike Place | D100: https://sushikashiba.com/ | E100: Japanese/Sushi | F100: $$$$ | G100: omakase;iconic;chef-driven | H100: Sushi Kashiba is Shiro Kashiba's masterwork - the Jiro-trained legend behind the counter, turning out 20-plus-course omakase of pristine, market-driven fish near Pike Place. Sit at the bar and put yourself in his hands. The city's benchmark sushi date: precise, unhurried, and worth the wait for a counter seat. | I100: Restaurant | J100: 86 Pine St Ste 1, Seattle, WA 98101 | K100: (206) 441-8844 | L100: Edomae omakase | M100: Mon/Wed/Thu/Sun 5-9pm; Fri-Sat 5-9:30pm | N100: Yes | O100: OpenTable (+ walk-in counter) | P100: N | Q100: N | R100: Y | S100: Iconic; Refined; Counter; Romantic | T100: Moderate | U100: 5 | V100: N | X100: 1589+ | Y100: Shiro Kashiba's omakase flagship; Jiro-trained master | Z100: Chef's omakase | AA100: Seasonal nigiri | AB100: $90-160 omakase | AC100: https://sushikashiba.com/ | AD100: HTML | AI100: 2026-06 | AJ100: 2026-06-19 | AK100: Enriched
...
